whitebox_plugin_gps_display_icons/pyproject.toml
whitebox_plugin_gps_display_icons/__init__.py
whitebox_plugin_gps_display_icons/static/whitebox_plugin_gps_display_icons/assets/plane.svg
whitebox_plugin_gps_display_icons/static/whitebox_plugin_gps_display_icons/whitebox_marker_override.mjs
whitebox_plugin_gps_display_icons/whitebox_plugin_gps_display_icons.py
whitebox_test_plugin_gps_display_icons/__init__.py
whitebox_test_plugin_gps_display_icons/test_whitebox_plugin_gps_display.py
whitebox_plugin_gps_display_icons-0.1.3.dist-info/LICENSE
whitebox_plugin_gps_display_icons-0.1.3.dist-info/METADATA
whitebox_plugin_gps_display_icons-0.1.3.dist-info/WHEEL
whitebox_plugin_gps_display_icons-0.1.3.dist-info/RECORD
