Metadata-Version: 2.3
Name: whitebox-plugin-gps-display-icons
Version: 0.1.3
Summary: A plugin for whitebox to display alternative GPS icons on the GPS display
License: GNU Affero General Public License v3
Author: Milos
Author-email: hello@klined.org
Requires-Python: >=3.10.0
Classifier: License :: Other/Proprietary License
Classifier: Programming Language :: Python :: 3
Classifier: Programming Language :: Python :: 3.10
Classifier: Programming Language :: Python :: 3.11
Classifier: Programming Language :: Python :: 3.12
Classifier: Programming Language :: Python :: 3.13
